pydataspace/__init__.py
pydataspace/data/federatedIdentifier.yaml
pydataspace/federatedIdentifier/__init__.py
pydataspace/federatedIdentifier/context.py
pydataspace/federatedIdentifier/federatedIdentifier.py
pydataspace/federatedIdentifier/objectDependencies.py
pydataspace_federatedIdentifier-0.0.0.13.dist-info/METADATA
pydataspace_federatedIdentifier-0.0.0.13.dist-info/WHEEL
pydataspace_federatedIdentifier-0.0.0.13.dist-info/top_level.txt
pydataspace_federatedIdentifier-0.0.0.13.dist-info/RECORD
